miksi_ai_sdk-0.0.21.dist-info/RECORD
miksi_ai_sdk-0.0.21.dist-info/METADATA
miksi_ai_sdk-0.0.21.dist-info/WHEEL
miksi_ai_sdk-0.0.21.dist-info/top_level.txt
miksi_ai_sdk/__init__.py
miksi_ai_sdk/master.cpython-39-x86_64-linux-gnu.so
miksi_ai_sdk/agent.cpython-39-x86_64-linux-gnu.so
miksi_ai_sdk/api.cpython-39-x86_64-linux-gnu.so
miksi_ai_sdk/pythontool.cpython-39-x86_64-linux-gnu.so
miksi_ai_sdk/sqltool.cpython-39-x86_64-linux-gnu.so
miksi_ai_sdk/utils.cpython-39-x86_64-linux-gnu.so
