Metadata-Version: 2.1
Name: miksi-ai-sdk
Version: 0.0.21
Summary: Miksi-AI empowers your BI
Home-page: https://github.com/Miksi-io/Custom-Agent
Author: RichardKaranuMbuti
Author-email: officialforrichardk@gmail.com
License: UNKNOWN
Platform: UNKNOWN
Classifier: Programming Language :: Python :: 3
Classifier: License :: OSI Approved :: MIT License
Classifier: Operating System :: OS Independent
Requires-Python: >=3.6
Requires-Dist: aiohttp (==3.9.3)
Requires-Dist: aiosignal (==1.3.1)
Requires-Dist: annotated-types (==0.6.0)
Requires-Dist: anyio (==4.3.0)
Requires-Dist: attrs (==23.2.0)
Requires-Dist: certifi (==2024.2.2)
Requires-Dist: charset-normalizer (==3.3.2)
Requires-Dist: Cython (==3.0.9)
Requires-Dist: dataclasses-json (==0.6.4)
Requires-Dist: distro (==1.9.0)
Requires-Dist: frozenlist (==1.4.1)
Requires-Dist: greenlet (==3.0.3)
Requires-Dist: h11 (==0.14.0)
Requires-Dist: httpcore (==1.0.4)
Requires-Dist: httpx (==0.27.0)
Requires-Dist: idna (==3.6)
Requires-Dist: jsonpatch (==1.33)
Requires-Dist: jsonpointer (==2.4)
Requires-Dist: langchain (==0.1.10)
Requires-Dist: langchain-community (==0.0.25)
Requires-Dist: langchain-core (==0.1.28)
Requires-Dist: langchain-openai (==0.0.8)
Requires-Dist: langchain-text-splitters (==0.0.1)
Requires-Dist: langsmith (==0.1.13)
Requires-Dist: marshmallow (==3.21.0)
Requires-Dist: multidict (==6.0.5)
Requires-Dist: mypy-extensions (==1.0.0)
Requires-Dist: numpy (==1.26.4)
Requires-Dist: openai (==1.13.3)
Requires-Dist: orjson (==3.9.15)
Requires-Dist: packaging (==23.2)
Requires-Dist: psycopg2-binary (==2.9.9)
Requires-Dist: pydantic (==2.6.3)
Requires-Dist: pydantic-core (==2.16.3)
Requires-Dist: PyMySQL (==1.1.0)
Requires-Dist: pyodbc (==5.1.0)
Requires-Dist: python-dotenv (==1.0.1)
Requires-Dist: PyYAML (==6.0.1)
Requires-Dist: regex (==2023.12.25)
Requires-Dist: requests (==2.31.0)
Requires-Dist: sniffio (==1.3.1)
Requires-Dist: SQLAlchemy (==2.0.27)
Requires-Dist: tenacity (==8.2.3)
Requires-Dist: tiktoken (==0.6.0)
Requires-Dist: tqdm (==4.66.2)
Requires-Dist: typing-inspect (==0.9.0)
Requires-Dist: typing-extensions (==4.10.0)
Requires-Dist: urllib3 (==2.2.1)
Requires-Dist: yarl (==1.9.4)
